LICENSE
README.rst
setup.py
consoleprinter/__init__.py
consoleprinter.egg-info/PKG-INFO
consoleprinter.egg-info/SOURCES.txt
consoleprinter.egg-info/dependency_links.txt
consoleprinter.egg-info/requires.txt
consoleprinter.egg-info/top_level.txt
consoleprinter.egg-info/zip-safe