Metadata-Version: 2.1
Name: consoleprinter
Version: 95
Summary: Console printer with linenumbers, stacktraces, logging, conversions and coloring..
Home-page: https://github.com/erikdejonge/consoleprinter
Author: Erik de Jonge
Author-email: erik@a8.nl
License: GPL
Classifier: Programming Language :: Python
Classifier: Programming Language :: Python :: 3
Classifier: Intended Audience :: Developers
Classifier: License :: OSI Approved :: GNU Library or Lesser General Public License (LGPL)
Classifier: Operating System :: POSIX
Classifier: Topic :: Software Development :: Libraries :: Python Modules
Classifier: Topic :: System
License-File: LICENSE
